wise_agent_toolkit/__init__.py
wise_agent_toolkit/api.py
wise_agent_toolkit/configuration.py
wise_agent_toolkit/functions.py
wise_agent_toolkit/prompts.py
wise_agent_toolkit/schema.py
wise_agent_toolkit/tools.py
wise_agent_toolkit/autogen/__init__.py
wise_agent_toolkit/crewai/__init__.py
wise_agent_toolkit/integrations/__init__.py
wise_agent_toolkit/integrations/base.py
wise_agent_toolkit/langchain/__init__.py
wise_agent_toolkit/langchain/tool.py
wise_agent_toolkit/langchain/toolkit.py
wise_agent_toolkit/mcp/__init__.py
wise_agent_toolkit/mcp/__main__.py
wise_agent_toolkit/mcp/server.py
wise_agent_toolkit/mcp/tool.py
wise_agent_toolkit/mcp/toolkit.py
wise_agent_toolkit-0.3.5.dist-info/licenses/LICENSE
wise_agent_toolkit-0.3.5.dist-info/METADATA
wise_agent_toolkit-0.3.5.dist-info/WHEEL
wise_agent_toolkit-0.3.5.dist-info/top_level.txt
wise_agent_toolkit-0.3.5.dist-info/RECORD
