Metadata-Version: 2.4
Name: wise-agent-toolkit
Version: 0.3.5
Summary: The Wise Agent Toolkit enables the integration of various AI frameworks and libraries with Wise APIs to create and manage transfers programmatically.
Author-email: Max Ploter <maksim.ploter@gmail.com>
License-Expression: MIT
Project-URL: Homepage, https://github.com/maxploter/wise-agent-toolkit
Project-URL: Repository, https://github.com/maxploter/wise-agent-toolkit
Project-URL: Documentation, https://github.com/maxploter/wise-agent-toolkit
Keywords: wise,transferwise,ai,agents,langchain
Classifier: Development Status :: 3 - Alpha
Classifier: Intended Audience :: Developers
Classifier: Programming Language :: Python :: 3
Classifier: Programming Language :: Python :: 3.11
Classifier: Programming Language :: Python :: 3.12
Requires-Python: >=3.11
License-File: LICENSE
Requires-Dist: wise-api-client>=0.6.0
Requires-Dist: pydantic>=2.10
Provides-Extra: langchain
Requires-Dist: langchain>=0.3.0; extra == "langchain"
Requires-Dist: langchain-openai>=0.2.0; extra == "langchain"
Requires-Dist: openai>=1.66.0; extra == "langchain"
Provides-Extra: mcp
Requires-Dist: mcp>=1.0.0; extra == "mcp"
Provides-Extra: dev
Requires-Dist: pytest>=7.0; extra == "dev"
Requires-Dist: pytest-cov>=4.0; extra == "dev"
Requires-Dist: black>=23.0; extra == "dev"
Requires-Dist: isort>=5.0; extra == "dev"
Requires-Dist: flake8>=6.0; extra == "dev"
Provides-Extra: all
Requires-Dist: wise-agent-toolkit[langchain]; extra == "all"
Requires-Dist: wise-agent-toolkit[mcp]; extra == "all"
Dynamic: license-file
